bbm25_haystack/__about__.py
bbm25_haystack/__init__.py
bbm25_haystack/bbm25_retriever.py
bbm25_haystack/bbm25_store.py
bbm25_haystack/default.model
bbm25_haystack/filters.py
bbm25_haystack-0.2.1.dist-info/METADATA
bbm25_haystack-0.2.1.dist-info/WHEEL
bbm25_haystack-0.2.1.dist-info/licenses/LICENSE
bbm25_haystack-0.2.1.dist-info/RECORD
