Metadata-Version: 2.3
Name: bbm25-haystack
Version: 0.2.1
Summary: Haystack 2.x In-memory Document Store with Enhanced Efficiency
Project-URL: Documentation, https://github.com/Guest400123064/bbm25-haystack#readme
Project-URL: Issues, https://github.com/Guest400123064/bbm25-haystack/issues
Project-URL: Source, https://github.com/Guest400123064/bbm25-haystack
Author-email: Yuxuan Wang <wangy49@seas.upenn.edu>
License-Expression: Apache-2.0
License-File: LICENSE
Keywords: BM25,Document Search,Haystack,LLM Agent,RAG
Classifier: Development Status :: 4 - Beta
Classifier: Programming Language :: Python
Classifier: Programming Language :: Python :: 3.9
Classifier: Programming Language :: Python :: 3.10
Classifier: Programming Language :: Python :: 3.11
Classifier: Programming Language :: Python :: Implementation :: CPython
Classifier: Programming Language :: Python :: Implementation :: PyPy
Requires-Python: >=3.9
Requires-Dist: haystack-ai
Requires-Dist: sentencepiece
Requires-Dist: typing-extensions
